[{"id": 28997, "title": "FreeBuf\u5468\u62a5 |Android\u94f6\u884c\u6076\u610f\u8f6f\u4ef6BrazKing\uff1b\u9ed1\u5ba224\u5c0f\u65f6\u5185\u53ef\u4ee5\u653b\u7834\u90e8\u5206\u871c\u7f50", "url": "https://www.freebuf.com/news/306097.html", "create_at": "2021-11-27 10:01", "site_name": "freebuf"}, {"id": 28996, "title": "\u6743\u9650\u7ef4\u6301\u7b80\u8981\u5206\u6790", "url": "https://www.freebuf.com/articles/web/303896.html", "create_at": "2021-11-27 08:59", "site_name": "freebuf"}, {"id": 28995, "title": "\u90e8\u5206\u7f8e\u56fd\u56fd\u9632\u627f\u5305\u5546\u6781\u6613\u906d\u53d7\u52d2\u7d22\u8f6f\u4ef6\u653b\u51fb", "url": "https://www.freebuf.com/news/306168.html", "create_at": "2021-11-27 08:59", "site_name": "freebuf"}]