[{"id": 27050, "title": "\u8ffd\u8e2aLockBit\u52d2\u7d22\u56e2\u4f19\u7528\u4e8e\u6570\u636e\u7a83\u53d6\u7684\u57fa\u7840\u8bbe\u65bd", "url": "https://www.freebuf.com/articles/network/290425.html", "create_at": "2021-10-25 09:03", "site_name": "freebuf"}, {"id": 27049, "title": "FreeBuf\u65e9\u62a5 | 20\u591a\u5bb6\u4f01\u4e1a\u627f\u8bfa\u4e0d\u76d1\u542c\u4e2a\u4eba\u9690\u79c1\uff1b\u592e\u89c6\u66dd\u5149\u5927\u91cf\u4eba\u8138\u7167\u7247\u51e0\u6bdb\u94b1\u4ef7\u683c\u88ab\u552e", "url": "https://www.freebuf.com/news/292657.html", "create_at": "2021-10-25 09:03", "site_name": "freebuf"}]