[{"id": 20636, "title": "[\u6570\u4e16\u54a8\u8be2] \u6700\u5371\u9669\u8f6f\u4ef6\u7f3a\u9677\u5217\u8868(2021 CWE Top 25)\u610f\u5473\u4ec0\u4e48\uff1f", "url": "https://mp.weixin.qq.com/s?__biz=MzkxNzA3MTgyNg==&mid=2247490123&idx=1&sn=e28742ecd78e7e0f613bf1485184589e", "create_at": "2021-08-19 00:30", "site_name": "\u5fae\u4fe1\u516c\u4f17\u53f7"}, {"id": 20635, "title": "[Hacking\u9ed1\u767d\u7ea2] \u57df\u6e17\u900f\u4e4b\uff08\u767d\u94f6\u7968\u636e\u5229\u7528\uff09", "url": "https://mp.weixin.qq.com/s?__biz=Mzg2NDYwMDA1NA==&mid=2247490236&idx=1&sn=a9c9f857423ec0aedd6bd7b7cdd9f339", "create_at": "2021-08-19 00:30", "site_name": "\u5fae\u4fe1\u516c\u4f17\u53f7"}]