[{"id": 6000, "title": "\u653b\u9632\u5bf9\u6297+\u6eaf\u6e90\u53cd\u5236\uff0c\u871c\u7f50\u5b9e\u6218\u5206\u4eab\u5b9e\u5f55", "url": "http://vulsee.com/archives/vulsee_2021/0317_13960.html", "create_at": "2021-03-17 01:35", "site_name": "\u5fae\u6444\u4fe1\u606f\u7f51"}, {"id": 5999, "title": "HW\u5fc5\u5907-\u871c\u7f50\u5982\u4f55\u5728\u653b\u9632\u6f14\u7ec3\u4e2d\u6218\u672f\u90e8\u9632", "url": "https://mp.weixin.qq.com/s?__biz=MzUyMTA0MjQ4NA==&mid=2247503447&idx=1&sn=5a703fc6e52e021b8199a5701a77e6a4", "create_at": "2021-03-17 01:35", "site_name": "LemonSec"}]