[{"id": 50081, "title": "[\u5a01\u80c1\u68f1\u955c] \u90e8\u5206\u7ec8\u7aef\u5b89\u5168\u9632\u62a4\u8f6f\u4ef6\u7684 DNSAML \u670d\u52a1\u5b58\u5728\u7f3a\u9677", "url": "https://mp.weixin.qq.com/s?__biz=MzkyMzE5ODExNQ==&mid=2247485221&idx=1&sn=5ecdb04a6ad9619456aa38aa94d350b8", "create_at": "2022-05-17 05:20", "site_name": "\u5fae\u4fe1\u516c\u4f17\u53f7"}, {"id": 50080, "title": "xpath\u5254\u9664\u6240\u9009\u90e8\u5206\u4e2d\u7684\u5143\u7d20", "url": "https://vulsee.com/archives/vulsee_2022/0517_16364.html", "create_at": "2022-05-17 01:29", "site_name": "\u5fae\u6444\u4fe1\u606f\u7f51"}, {"id": 50079, "title": "\u4e91\u4e0a\u653b\u9632\u4e8c\u4e09\u4e8b\uff08\u7eed\uff09", "url": "https://wiki.ioin.in/url/m03o", "create_at": "2022-05-17 00:38", "site_name": "Sec-News"}, {"id": 50078, "title": "\u7f51\u7edc\u5b89\u5168\u521b\u4e1a\u4ece0\u52301-\u6f14\u8bb2\u5b9e\u5f55", "url": "https://mp.weixin.qq.com/s/0uTkCQHtCySO9ydEjUMU8g", "create_at": "2022-05-17 00:38", "site_name": "sec-wiki"}, {"id": 50077, "title": "[\u58a8\u96ea\u98d8\u5f71] edusrc\u7528\u6237\u6570\u636e\u5206\u6790--\u6d4f\u89c8\u5668\u811a\u672c", "url": "https://mp.weixin.qq.com/s?__biz=MzI3NzI4OTkyNw==&mid=2247488352&idx=1&sn=c5fb29c3c86ec61656a11d0085c0796b", "create_at": "2022-05-17 00:37", "site_name": "\u5fae\u4fe1\u516c\u4f17\u53f7"}, {"id": 50076, "title": "[IoVSecurity] \u6c7d\u8f66\u884c\u4e1a\u7684\u7f51\u7edc\u5b89\u5168\u6311\u6218", "url": "https://mp.weixin.qq.com/s?__biz=MzU2MDk1Nzg2MQ==&mid=2247539125&idx=3&sn=247233acec312935e405a2b6c430e193", "create_at": "2022-05-17 00:37", "site_name": "\u5fae\u4fe1\u516c\u4f17\u53f7"}, {"id": 50075, "title": "[IoVSecurity] \u5982\u4f55\u5efa\u7acb\u4ea7\u54c1\u5b89\u5168\u4e8b\u4ef6\u54cd\u5e94\u56e2\u961f FIRST PSIRT \u6846\u67b6\u4e0e PROOF \u96c6\u6210", "url": "https://mp.weixin.qq.com/s?__biz=MzU2MDk1Nzg2MQ==&mid=2247539125&idx=2&sn=8cec8f61f2a843c68d7d2bbc40f5ce5e", "create_at": "2022-05-17 00:37", "site_name": "\u5fae\u4fe1\u516c\u4f17\u53f7"}, {"id": 50074, "title": "[IoVSecurity] \u4e94\u661f\u6c7d\u8f66\u7f51\u7edc\u5b89\u5168\u6846\u67b6", "url": "https://mp.weixin.qq.com/s?__biz=MzU2MDk1Nzg2MQ==&mid=2247539125&idx=1&sn=439d5314311d5c13334cc0e970237e2c", "create_at": "2022-05-17 00:37", "site_name": "\u5fae\u4fe1\u516c\u4f17\u53f7"}, {"id": 50073, "title": "[SecWiki] SecWiki\u5468\u520a\uff08\u7b2c428\u671f\uff09", "url": "https://mp.weixin.qq.com/s?__biz=MjM5NDM1OTM0Mg==&mid=2651052522&idx=1&sn=b8bab7d22f5d7166b29d570121865210", "create_at": "2022-05-17 00:37", "site_name": "\u5fae\u4fe1\u516c\u4f17\u53f7"}, {"id": 50072, "title": "[\u5b89\u5168\u6f0f\u6d1e\u590d\u73b0] WeiPHP5.0 \u00e4\u00bb\u00bb\u00e6\u201e\u008f\u00e7\u201d\u00a8\u00e6\u02c6\u00b7Cookie\u00e4\u00bc\u00aa\u00e9\u20ac", "url": "https://mp.weixin.qq.com/s?__biz=Mzg2Mzc2OTM0OQ==&mid=2247483819&idx=1&sn=de6383fd912dfabbef7b475e421ebce4", "create_at": "2022-05-17 00:37", "site_name": "\u5fae\u4fe1\u516c\u4f17\u53f7"}, {"id": 50071, "title": "[Hacking\u9ed1\u767d\u7ea2] \u30102022HVV\u7cfb\u5217\u3011|7-Windows\u4e3b\u673a\u5165\u4fb5\u75d5\u8ff9\u6392\u67e5\u529e\u6cd5", "url": "https://mp.weixin.qq.com/s?__biz=Mzg2NDYwMDA1NA==&mid=2247514982&idx=1&sn=2d633a5be7eb41da4a1ce35e2293c3bc", "create_at": "2022-05-17 00:37", "site_name": "\u5fae\u4fe1\u516c\u4f17\u53f7"}]