[{"id": 78180, "title": "[Linux\u4e2d\u56fd] \u5982\u4f55\u5728\u7b14\u8bb0\u672c\u7535\u8111\u5408\u76d6\u65f6\u4e0d\u6302\u8d77 Ubuntu | Linux \u4e2d\u56fd", "url": "https://i.hacking8.com/url/6kF9", "create_at": "2022-09-11 10:41", "site_name": "\u5fae\u4fe1\u516c\u4f17\u53f7"}, {"id": 78179, "title": "[\u6c83\u514b\u5b66\u5b89\u5168] JAVA\u5b89\u5168|\u57fa\u7840\u7bc7\uff1a\u53cd\u5c04\u673a\u5236\u4e4b\u5e38\u89c1ReflectionAPI\u4f7f\u7528", "url": "https://i.hacking8.com/url/6kFa", "create_at": "2022-09-11 10:41", "site_name": "\u5fae\u4fe1\u516c\u4f17\u53f7"}, {"id": 78178, "title": "[\u6cb3\u5357\u7b49\u7ea7\u4fdd\u62a4\u6d4b\u8bc4] \u5468\u672b\u8c08\u7b49\u4fdd\uff1a\u7b49\u7ea7\u4fdd\u62a4\u5bf9\u8c61\u7684\u5b9a\u7ea7\u4e0e\u4fdd\u62a4", "url": "https://mp.weixin.qq.com/s?__biz=Mzg2NjY2MTI3Mg==&mid=2247487241&idx=1&sn=25b8c572c98f19ca7b88f07a019ee0dd", "create_at": "2022-09-11 10:40", "site_name": "\u5fae\u4fe1\u516c\u4f17\u53f7"}, {"id": 78177, "title": "[\u8fea\u54e5\u8bb2\u4e8b] sqli\u5b66\u4e60\u7b14\u8bb0\u7cfb\u5217-\u7ed5\u8fc7Kona WAF", "url": "https://mp.weixin.qq.com/s?__biz=MzIzMTIzNTM0MA==&mid=2247486294&idx=1&sn=8a095a4b5526e582c17dba3abff4b167", "create_at": "2022-09-11 10:40", "site_name": "\u5fae\u4fe1\u516c\u4f17\u53f7"}, {"id": 78176, "title": "[\u7f51\u7edc\u5b89\u5168\u89c2] \u7f51\u7edc\u5b89\u5168\u7684\u4e09\u5927\u652f\u67f1\u548c\u653b\u51fb\u5411\u91cf", "url": "https://mp.weixin.qq.com/s?__biz=MzIxNzUxNzA2NQ==&mid=2247494915&idx=1&sn=9a185bb4f19813af6182a95802e90d40", "create_at": "2022-09-11 10:40", "site_name": "\u5fae\u4fe1\u516c\u4f17\u53f7"}, {"id": 78175, "title": "[\u5b89\u5168\u5185\u53c2] GhostSec\u9ed1\u5ba2\u7ec4\u7ec7\u653b\u9677\u4e86\u4ee5\u8272\u521755\u4e2aBerghof PLC\u5de5\u63a7\u8bbe\u5907", "url": "https://mp.weixin.qq.com/s?__biz=MzI4NDY2MDMwMw==&mid=2247505863&idx=4&sn=352bc521a95834f247ba126000501d2d", "create_at": "2022-09-11 10:40", "site_name": "\u5fae\u4fe1\u516c\u4f17\u53f7"}, {"id": 78174, "title": "[\u5b89\u5168\u5185\u53c2] \u300a\u8eab\u4efd\u653b\u51fb\u5411\u91cf\u300b\u2460\uff1a\u91cd\u65b0\u8ba4\u8bc6\u4f01\u4e1a\u8eab\u4efd", "url": "https://mp.weixin.qq.com/s?__biz=MzI4NDY2MDMwMw==&mid=2247505866&idx=1&sn=2e1c5e141568928bff936b63b2102eea", "create_at": "2022-09-11 10:40", "site_name": "\u5fae\u4fe1\u516c\u4f17\u53f7"}, {"id": 78173, "title": "[\u5947\u5b89\u4fe1\u5a01\u80c1\u60c5\u62a5\u4e2d\u5fc3] \u9526\u4e66\u9065\u5bc4\uff0c\u795d\u5927\u5bb6\u4e2d\u79cb\u5feb\u4e50\u2014\u2014\u5947\u5b89\u4fe1\u5a01\u80c1\u60c5\u62a5\u4e2d\u5fc3", "url": "https://mp.weixin.qq.com/s?__biz=MzI2MDc2MDA4OA==&mid=2247503670&idx=1&sn=8f427385d3e56c028a3449176fec6717", "create_at": "2022-09-11 10:40", "site_name": "\u5fae\u4fe1\u516c\u4f17\u53f7"}, {"id": 78172, "title": "[\u54c6\u5566\u5b89\u5168] \u5e38\u89c1\u6570\u636e\u5e93\u7b49\u4fdd\u6d4b\u8bc4\u68c0\u67e5\u547d\u4ee4\u6c47\u603b", "url": "https://mp.weixin.qq.com/s?__biz=Mzg2NzUzNzk1Mw==&mid=2247494117&idx=2&sn=ff2a50ef47e325c86099b0d8607d6e8c", "create_at": "2022-09-11 10:40", "site_name": "\u5fae\u4fe1\u516c\u4f17\u53f7"}, {"id": 78171, "title": "[\u54c6\u5566\u5b89\u5168] Android\u5206\u6790system_server CPU\u5360\u7528\u9ad8\u7684\u65b9\u6cd5", "url": "https://mp.weixin.qq.com/s?__biz=Mzg2NzUzNzk1Mw==&mid=2247494117&idx=1&sn=9f6b8cb7f011270aacb2a7d5e732bea0", "create_at": "2022-09-11 10:40", "site_name": "\u5fae\u4fe1\u516c\u4f17\u53f7"}, {"id": 78170, "title": "[EchoSec] \u795e\u5175\u5229\u5668 | \u5206\u4eab\u4e00\u6b3e\u57df\u6e17\u900f\u5168\u65b9\u4f4d\u626b\u63cf\u5229\u7528Tools", "url": "https://mp.weixin.qq.com/s?__biz=MzU3MTU3NTY2NA==&mid=2247485757&idx=1&sn=f3438bf038278af5441d23e15fca99ed", "create_at": "2022-09-11 10:40", "site_name": "\u5fae\u4fe1\u516c\u4f17\u53f7"}, {"id": 78169, "title": "[\u68c9\u82b1\u7cd6\u7f51\u7edc\u5b89\u5168\u5708] Acunetix Premium v14.9.220830118\u7834\u89e3", "url": "https://mp.weixin.qq.com/s?__biz=Mzg5NTYwMDIyOA==&mid=2247488731&idx=1&sn=984e59fb508d7f08762e1f1c1a0ddae5", "create_at": "2022-09-11 10:40", "site_name": "\u5fae\u4fe1\u516c\u4f17\u53f7"}, {"id": 78168, "title": "[\u83dc\u9e1f\u5b66\u4fe1\u5b89] src-\u6f0f\u6d1e\u6316\u6398-getshell", "url": "https://mp.weixin.qq.com/s?__biz=MzU2NzY5MzI5Ng==&mid=2247492022&idx=1&sn=a039ae9f536b5273946f4af116f4630a", "create_at": "2022-09-11 10:40", "site_name": "\u5fae\u4fe1\u516c\u4f17\u53f7"}, {"id": 78167, "title": "[Th0r\u5b89\u5168] \u4e2d\u79cb\u798f\u5229|\u5916\u4f01\u5185\u63a8", "url": "https://i.hacking8.com/url/6kMe", "create_at": "2022-09-11 10:40", "site_name": "\u5fae\u4fe1\u516c\u4f17\u53f7"}, {"id": 78166, "title": "[\u7cfb\u7edf\u5b89\u5168\u8fd0\u7ef4] \u3010\u5206\u4eab\u3011\u8bb0\u4e00\u6b21\u4eceshiro-550\u5230\u5185\u7f51\u6e17\u900f\u7684\u5168\u8fc7\u7a0b", "url": "https://i.hacking8.com/url/6kMf", "create_at": "2022-09-11 10:40", "site_name": "\u5fae\u4fe1\u516c\u4f17\u53f7"}, {"id": 78165, "title": "[\u7cfb\u7edf\u5b89\u5168\u8fd0\u7ef4] \u5185\u7f51\u4fe1\u606f\u641c\u96c6\u5bc6\u7801\u8bfb\u53d6\u548c\u952e\u76d8\u8bb0\u5f55", "url": "https://i.hacking8.com/url/6kMg", "create_at": "2022-09-11 10:40", "site_name": "\u5fae\u4fe1\u516c\u4f17\u53f7"}, {"id": 78164, "title": "[kali\u9ed1\u5ba2\u7b14\u8bb0] \u901f\u968f\u70ed\u52a8\u2014\u8ba9\u6811\u8393\u6d3e\u98ce\u6247\u968f\u6e29\u5ea6\u53d8\u5316\u800c\u52a8", "url": "https://i.hacking8.com/url/6kMh", "create_at": "2022-09-11 10:40", "site_name": "\u5fae\u4fe1\u516c\u4f17\u53f7"}, {"id": 78163, "title": "[\u7eff\u76df\u79d1\u6280] \u7f51\u5b89\u5468\u79d1\u666e\u7cfb\u5217\uff08\u516b\uff09\uff1a\u5982\u4f55\u907f\u514d\u201c\u7269\u7406\u5165\u4fb5\u201d\uff1f", "url": "https://i.hacking8.com/url/6kMH", "create_at": "2022-09-11 10:39", "site_name": "\u5fae\u4fe1\u516c\u4f17\u53f7"}, {"id": 78162, "title": "[\u7eff\u76df\u79d1\u6280] \u805a\u71262022\u7f51\u5b89\u5468\uff5c\u964c\u751f\u8ba4\u8bc1\u9700\u8c28\u614e\uff0c\u83ab\u8d2a\u4fbf\u5b9c\u88ab\u4eba\u5751", "url": "https://i.hacking8.com/url/6kMI", "create_at": "2022-09-11 10:39", "site_name": "\u5fae\u4fe1\u516c\u4f17\u53f7"}, {"id": 78161, "title": "[\u83dc\u9e1f\u5b66\u5b89\u5168] \u5e72\u8d27 | \u5168\u7f51\u4f18\u79c0\u7684\u653b\u9632\u6e17\u900f\u5de5\u5177\u603b\u7ed3", "url": "https://i.hacking8.com/url/6kMJ", "create_at": "2022-09-11 10:39", "site_name": "\u5fae\u4fe1\u516c\u4f17\u53f7"}, {"id": 78160, "title": "[\u90d1\u5dde\u7f51\u7edc\u5b89\u5168] API\u5b89\u5168\uff1a2022\u5e74\u8bbf\u95ee\u63a7\u5236\u4e2d\u65ad\u3001\u6ce8\u5165\u653b\u51fb\u56f0\u6270\u4f01\u4e1a\u5b89\u5168\u683c\u5c40", "url": "https://i.hacking8.com/url/6kMK", "create_at": "2022-09-11 10:38", "site_name": "\u5fae\u4fe1\u516c\u4f17\u53f7"}, {"id": 78159, "title": "[HACK\u4e4b\u9053] \u6bd5\u4e1a\u5c31\u641e\u722c\u866b\u768400\u540e\u89c1\u591a\u4e86\uff0c\u4f46\u4e00\u53e3\u6c14\u8d5a12000\u7684\u8fd8\u662f\u7b2c\u4e00\u6b21\u89c1", "url": "https://i.hacking8.com/url/6kNF", "create_at": "2022-09-11 10:38", "site_name": "\u5fae\u4fe1\u516c\u4f17\u53f7"}, {"id": 78158, "title": "[\u5b89\u6052\u4fe1\u606f] \u8427\u5c71\u6570\u636e\u5b89\u5168\u8054\u5408\u5b9e\u9a8c\u5ba4\u5b75\u5316\u4ea7\u54c1\u5165\u9009\u676d\u5dde\u5e02\u6570\u5b57\u5316\u6539\u9769\u7f51\u7edc\u5b89\u5168\u4f18\u79c0\u6848\u4f8b", "url": "https://i.hacking8.com/url/6kNG", "create_at": "2022-09-11 10:38", "site_name": "\u5fae\u4fe1\u516c\u4f17\u53f7"}, {"id": 78157, "title": "[\u9ed1\u767d\u4e4b\u9053] \u8bb0\u4e00\u6b21\u4eceshiro-550\u5230\u5185\u7f51\u6e17\u900f\u7684\u5168\u8fc7\u7a0b", "url": "https://i.hacking8.com/url/6kNH", "create_at": "2022-09-11 10:37", "site_name": "\u5fae\u4fe1\u516c\u4f17\u53f7"}, {"id": 78156, "title": "[\u9ed1\u767d\u4e4b\u9053] Web\u5e94\u7528\u5b89\u5168\u9632\u62a4\u7684\u5341\u5927\u8bef\u533a", "url": "https://i.hacking8.com/url/6kNI", "create_at": "2022-09-11 10:37", "site_name": "\u5fae\u4fe1\u516c\u4f17\u53f7"}, {"id": 78155, "title": "[\u9ed1\u767d\u4e4b\u9053] \u201c\u767e\u65e5\u884c\u52a8\u201d\u516c\u5b89\u6293\u83b71160\u540d\u9ed1\u5ba2\uff1bWordPress\u63d2\u4ef6\u66dd\u51fa\u96f6\u65e5\u6f0f\u6d1e\uff0c\u5df2\u88ab\u79ef\u6781\u5728\u91ce\u5229\u7528", "url": "https://i.hacking8.com/url/6kNJ", "create_at": "2022-09-11 10:37", "site_name": "\u5fae\u4fe1\u516c\u4f17\u53f7"}, {"id": 78154, "title": "[\u5206\u5e03\u5f0f\u5b9e\u9a8c\u5ba4] Apache Iceberg\uff0c\u503c\u5f97\u6211\u4eec\u91cd\u70b9\u5173\u6ce8", "url": "https://i.hacking8.com/url/6kNK", "create_at": "2022-09-11 10:36", "site_name": "\u5fae\u4fe1\u516c\u4f17\u53f7"}, {"id": 78153, "title": "[\u5b89\u5168\u5185\u53c2] \u4e2d\u79d1\u5927\u53d14\u4e07\u5c01\u201c\u514d\u8d39\u9001\u6708\u997c\u201d\u9493\u9c7c\u90ae\u4ef6\uff0c\u6821\u65b9\u79f0\u7cfb\u53cd\u8bc8\u6f14\u7ec3", "url": "https://mp.weixin.qq.com/s?__biz=MzI4NDY2MDMwMw==&mid=2247505872&idx=1&sn=e32cd222a74eb71e8de2c88ebc4bf012", "create_at": "2022-09-11 10:36", "site_name": "\u5fae\u4fe1\u516c\u4f17\u53f7"}, {"id": 78152, "title": "[\u542f\u660e\u661f\u8fb0\u7f51\u7edc\u7a7a\u95f4\u5b89\u5168\u5b66\u9662] \u76f4\u64ad\u9884\u544a\u4e28\u7ea2\u961f\u653b\u9632\u5206\u4eab\u4f1a\u7b2c\u516d\u671f\u300a\u5185\u7f51\u7a7f\u900f\u5b9e\u6218\u2014\u8fdb\u5165\u76ee\u6807\u5185\u7f51", "url": "https://mp.weixin.qq.com/s?__biz=MzUzNDg0NTc1NA==&mid=2247494002&idx=1&sn=9084e502ea96c2498aa45d5a6134d142", "create_at": "2022-09-11 10:36", "site_name": "\u5fae\u4fe1\u516c\u4f17\u53f7"}, {"id": 78151, "title": "[\u542c\u98ce\u5b89\u5168] JWT\u00e6\u201d\u00bb\u00e5\u2021\u00bb\u00e5\u00ad\u00a6\u00e4\u00b9", "url": "https://mp.weixin.qq.com/s?__biz=Mzg3NzIxMDYxMw==&mid=2247485309&idx=1&sn=a48ad4501e88ca3e590a4d5262a1c185", "create_at": "2022-09-11 10:35", "site_name": "\u5fae\u4fe1\u516c\u4f17\u53f7"}, {"id": 78150, "title": "[\u6e17\u900f\u5b89\u5168\u56e2\u961f] \u5e72\u8d27\uff5c\u6559\u4f60\u7528\u624b\u673a\u4ee3\u66ff\u5404\u7c7b\u95e8\u7981\u5361", "url": "https://mp.weixin.qq.com/s?__biz=MzkxNDAyNTY2NA==&mid=2247492316&idx=1&sn=6f53a1c1cfa481b4abf551d58a835c53", "create_at": "2022-09-11 10:35", "site_name": "\u5fae\u4fe1\u516c\u4f17\u53f7"}, {"id": 78149, "title": "WordPress\u63d2\u4ef6\u66dd\u51fa\u96f6\u65e5\u6f0f\u6d1e\uff0c\u5df2\u88ab\u79ef\u6781\u5728\u91ce\u5229\u7528", "url": "https://www.freebuf.com/news/344225.html", "create_at": "2022-09-11 10:34", "site_name": "freebuf"}, {"id": 78148, "title": "\u7f05\u7538\u6570\u636e\u5408\u89c4\u91cd\u70b9\u89e3\u8bfb", "url": "https://www.freebuf.com/articles/others-articles/343711.html", "create_at": "2022-09-11 10:34", "site_name": "freebuf"}, {"id": 78147, "title": "[\u5168\u7403\u6280\u672f\u5730\u56fe] \u7f8e\u56fdCURV\u578b\u9065\u63a7\u6f5c\u6c34\u5668\u53d1\u5c55\u6982\u8ff0", "url": "https://i.hacking8.com/url/6kou", "create_at": "2022-09-11 05:27", "site_name": "\u5fae\u4fe1\u516c\u4f17\u53f7"}, {"id": 78146, "title": "[\u8fdb\u51fb\u7684Coder] Kotlin\uff1a\u6211\u5e72\u7239\u662f Google \uff01", "url": "https://i.hacking8.com/url/6kov", "create_at": "2022-09-11 05:27", "site_name": "\u5fae\u4fe1\u516c\u4f17\u53f7"}, {"id": 78145, "title": "[\u8fdb\u51fb\u7684Coder] \u7528 Python \u7834\u89e3 WiFi \u5bc6\u7801\uff0c\u592a\u523a\u6fc0\u4e86\uff01", "url": "https://i.hacking8.com/url/6kow", "create_at": "2022-09-11 05:27", "site_name": "\u5fae\u4fe1\u516c\u4f17\u53f7"}, {"id": 78144, "title": "[Linux\u4e2d\u56fd] \u5373\u5c06\u5230\u6765\u7684 Fedora 37 \u524d\u77bb | Linux \u4e2d\u56fd", "url": "https://i.hacking8.com/url/6ks3", "create_at": "2022-09-11 03:27", "site_name": "\u5fae\u4fe1\u516c\u4f17\u53f7"}, {"id": 78143, "title": "[\u5b89\u5168\u5708] \u3010\u5b89\u5168\u5708\u3011\u6850\u4e61\u8b66\u65b9\u6253\u6389\u4e00\u4fb5\u72af\u516c\u6c11\u4e2a\u4eba\u4fe1\u606f\u72af\u7f6a\u56e2\u4f19", "url": "https://i.hacking8.com/url/6ks5", "create_at": "2022-09-11 03:26", "site_name": "\u5fae\u4fe1\u516c\u4f17\u53f7"}, {"id": 78142, "title": "[\u7a0b\u5e8f\u5458\u5927\u76ee] \u638c\u63e1\u8fd9\u4e9b SpringBoot \u542f\u52a8\u6269\u5c55\u70b9\uff0c\u5df2\u7ecf\u8d85\u8fc7 90% \u7684\u4eba\u4e86", "url": "https://i.hacking8.com/url/6kwV", "create_at": "2022-09-11 03:24", "site_name": "\u5fae\u4fe1\u516c\u4f17\u53f7"}, {"id": 78141, "title": "Attacking Firecracker: AWS' microVM Monitor Written in Rust", "url": "https://i.hacking8.com/url/6jjP", "create_at": "2022-09-11 03:20", "site_name": "\u817e\u8baf\u7384\u6b66\u5b9e\u9a8c\u5ba4"}, {"id": 78140, "title": "\u5229\u7528 RPCMon \u5de5\u5177\u76d1\u63a7 Windows \u5bb9\u5668\u7684\u901a\u4fe1", "url": "https://i.hacking8.com/url/6jjQ", "create_at": "2022-09-11 03:20", "site_name": "\u817e\u8baf\u7384\u6b66\u5b9e\u9a8c\u5ba4"}, {"id": 78139, "title": "[\u5229\u5203\u4fe1\u5b89] Cobalt Strike 4.7 Licensed (cobaltstrike.jar)", "url": "https://mp.weixin.qq.com/s?__biz=MzU1Mjk3MDY1OA==&mid=2247497682&idx=2&sn=c556f441d9ec12f9d27937623d6dfb83", "create_at": "2022-09-11 02:32", "site_name": "\u5fae\u4fe1\u516c\u4f17\u53f7"}, {"id": 78138, "title": "[\u5229\u5203\u4fe1\u5b89] \u8d85\u5168\u7f51\u7edc\u5b89\u5168\u6e17\u900f\u6d4b\u8bd5\u5de5\u5177\u5408\u96c6", "url": "https://mp.weixin.qq.com/s?__biz=MzU1Mjk3MDY1OA==&mid=2247497682&idx=1&sn=2d53712c9040bb67c923381e8c462b80", "create_at": "2022-09-11 02:32", "site_name": "\u5fae\u4fe1\u516c\u4f17\u53f7"}, {"id": 78137, "title": "\u539f\u751f\u53cd\u5e8f\u5217\u5316\u94fe jdk8u20 \u7684\u65b0\u6784\u9020", "url": "https://i.hacking8.com/url/6iPZ", "create_at": "2022-09-11 02:31", "site_name": "\u817e\u8baf\u7384\u6b66\u5b9e\u9a8c\u5ba4"}, {"id": 78136, "title": "Pwn2Own Miami 2022 \u6bd4\u8d5b AVEVA Edge SCADA \u8f6f\u4ef6\u4ee3\u7801\u6267\u884c\u6f0f\u6d1e\u7684\u5206\u6790\u548c\u5229\u7528", "url": "https://i.hacking8.com/url/6jia", "create_at": "2022-09-11 02:30", "site_name": "\u817e\u8baf\u7384\u6b66\u5b9e\u9a8c\u5ba4"}, {"id": 78135, "title": "[\u7eff\u76df\u79d1\u6280\u91d1\u878d\u4e8b\u4e1a\u90e8] \u4e2d\u79cb\u8282&\u6559\u5e08\u8282\u53cc\u8282\u5feb\u4e50", "url": "https://mp.weixin.qq.com/s?__biz=MzI2NDI5MTg4MA==&mid=2247492233&idx=1&sn=53e9451cfe5d9c53123bd2fbd73e8fb1", "create_at": "2022-09-11 01:27", "site_name": "\u5fae\u4fe1\u516c\u4f17\u53f7"}, {"id": 78134, "title": "[IoVSecurity] \u57fa\u4e8eTEE\u7684\u53ef\u4fe1\u6c7d\u8f66\u5a31\u4e50\u63a7\u5236\u7cfb\u7edf\u7684\u653b\u4e0e\u9632", "url": "https://mp.weixin.qq.com/s?__biz=MzU2MDk1Nzg2MQ==&mid=2247556507&idx=2&sn=026eb5bc0fbfd5c8610a9938f4cf7db3", "create_at": "2022-09-11 01:27", "site_name": "\u5fae\u4fe1\u516c\u4f17\u53f7"}, {"id": 78133, "title": "[IoVSecurity] TEE for Vehicle - \u57fa\u4e8eTEE\u7684\u8f66\u8054\u7f51\u5b89\u5168\u67b6\u6784", "url": "https://mp.weixin.qq.com/s?__biz=MzU2MDk1Nzg2MQ==&mid=2247556507&idx=1&sn=d6b01230b87ef7652c2840ba3bb93bdb", "create_at": "2022-09-11 01:27", "site_name": "\u5fae\u4fe1\u516c\u4f17\u53f7"}, {"id": 78132, "title": "[\u6570\u4e16\u54a8\u8be2] \u6570\u5b57\u5316\u8f6c\u578b\u4e0b\u5de5\u4e1a\u4e92\u8054\u7f51\u878d\u5408\u5b89\u5168", "url": "https://mp.weixin.qq.com/s?__biz=MzkxNzA3MTgyNg==&mid=2247495420&idx=2&sn=ba57b461b4655eb247b3fc76391ccb7d", "create_at": "2022-09-11 01:27", "site_name": "\u5fae\u4fe1\u516c\u4f17\u53f7"}, {"id": 78131, "title": "[\u6570\u4e16\u54a8\u8be2] \u56e0\u7f51\u7edc\u653b\u51fb\u65ad\u4ea4 \u4f0a\u6717\u9a7b\u963f\u5c14\u5df4\u5c3c\u4e9a\u5927\u4f7f\u9986\u906d\u7a81\u88ad", "url": "https://mp.weixin.qq.com/s?__biz=MzkxNzA3MTgyNg==&mid=2247495420&idx=1&sn=8826a3919968b29063ba839241cb235b", "create_at": "2022-09-11 01:27", "site_name": "\u5fae\u4fe1\u516c\u4f17\u53f7"}, {"id": 78130, "title": "[\u9752\u8863\u5341\u4e09\u697c\u98de\u82b1\u5802] \u6559\u5e08\u8282\u968f\u7b14", "url": "https://mp.weixin.qq.com/s?__biz=MzUzMjQyMDE3Ng==&mid=2247486175&idx=1&sn=7a880cff210580e4d43b987dd903b1e8", "create_at": "2022-09-11 01:27", "site_name": "\u5fae\u4fe1\u516c\u4f17\u53f7"}, {"id": 78129, "title": "[\u674e\u767d\u4f60\u597d] \u5e08\u5085\u4eec\u4e2d\u79cb\u5feb\u4e50\u54e6\uff01\u661f\u740381.5\u5927\u4f18\u60e0~", "url": "https://mp.weixin.qq.com/s?__biz=MzkwMzMwODg2Mw==&mid=2247493839&idx=1&sn=6bfc206139e28c91e15c38e3151de57c", "create_at": "2022-09-11 01:27", "site_name": "\u5fae\u4fe1\u516c\u4f17\u53f7"}, {"id": 78128, "title": "[\u8861\u9633\u4fe1\u5b89] PHP\u5b89\u5168\u5f00\u53d1\u6f2b\u8c08\uff08\u4e00\uff09", "url": "https://mp.weixin.qq.com/s?__biz=MzU2NDY2OTU4Nw==&mid=2247503944&idx=1&sn=33af42a323498d8ee663ecc5fcc5b9ec", "create_at": "2022-09-11 01:27", "site_name": "\u5fae\u4fe1\u516c\u4f17\u53f7"}, {"id": 78127, "title": "[HashRun\u5b89\u5168\u56e2\u961f] HashRun\u5b89\u5168\u56e2\u961fwp", "url": "https://mp.weixin.qq.com/s?__biz=MzkxODMyNjQ2MQ==&mid=2247484258&idx=1&sn=83545086df0f445bf7a518d03fcad68f", "create_at": "2022-09-11 01:27", "site_name": "\u5fae\u4fe1\u516c\u4f17\u53f7"}, {"id": 78126, "title": "[LemonSec] Windows -- \u5e94\u6025\u54cd\u5e94", "url": "https://mp.weixin.qq.com/s?__biz=MzUyMTA0MjQ4NA==&mid=2247535103&idx=3&sn=24c0b299faa0d67f10eb35e07abd1409", "create_at": "2022-09-11 01:27", "site_name": "\u5fae\u4fe1\u516c\u4f17\u53f7"}, {"id": 78125, "title": "[LemonSec] Linux -- \u5e94\u6025\u54cd\u5e94", "url": "https://mp.weixin.qq.com/s?__biz=MzUyMTA0MjQ4NA==&mid=2247535103&idx=2&sn=846da903ded096366f5073745223627c", "create_at": "2022-09-11 01:27", "site_name": "\u5fae\u4fe1\u516c\u4f17\u53f7"}, {"id": 78124, "title": "[LemonSec] \u8bb0\u5f55\u8fc7\u67d0\u5e38\u89c1WAF\u6700\u65b0\u7248", "url": "https://mp.weixin.qq.com/s?__biz=MzUyMTA0MjQ4NA==&mid=2247535103&idx=1&sn=2b2d18f218f11dddc76c29be8666ebea", "create_at": "2022-09-11 01:27", "site_name": "\u5fae\u4fe1\u516c\u4f17\u53f7"}, {"id": 78123, "title": "[web\u5b89\u5168\u5de5\u5177\u5e93] \u5185\u5b58\u9a6c\u6d41\u7a0b\u7406\u89e3\u4e0e\u624b\u5199 EXP", "url": "https://mp.weixin.qq.com/s?__biz=MzI4MDQ5MjY1Mg==&mid=2247504375&idx=1&sn=fb947126bb301ca6d945c5b2874e4b13", "create_at": "2022-09-11 01:27", "site_name": "\u5fae\u4fe1\u516c\u4f17\u53f7"}, {"id": 78122, "title": "[\u6a58\u732b\u5b66\u5b89\u5168] \u6536\u96c6\u5185\u5b58\u9a6c\u6253\u5165\u65b9\u5f0f", "url": "https://mp.weixin.qq.com/s?__biz=Mzg5OTY2NjUxMw==&mid=2247498381&idx=2&sn=e7f6862037b10a5f212223de7d492780", "create_at": "2022-09-11 01:27", "site_name": "\u5fae\u4fe1\u516c\u4f17\u53f7"}, {"id": 78121, "title": "[\u6a58\u732b\u5b66\u5b89\u5168] python\u811a\u672c\u68c0\u6d4b\u76ee\u6807ip\u662f\u5426\u5b58\u5728ftp\u7b11\u8138\u6f0f\u6d1e\uff08ftp\u540e\u95e8\u6f0f\u6d1e\uff09", "url": "https://mp.weixin.qq.com/s?__biz=Mzg5OTY2NjUxMw==&mid=2247498381&idx=1&sn=d767b254f696213d951e3419c6d8d43c", "create_at": "2022-09-11 01:27", "site_name": "\u5fae\u4fe1\u516c\u4f17\u53f7"}, {"id": 78120, "title": "[Linux\u4e2d\u56fd] \u5982\u4f55\u5728\u7b14\u8bb0\u672c\u7535\u8111\u5408\u76d6\u65f6\u4e0d\u6302\u8d77 Ubuntu | Linux \u4e2d\u56fd", "url": "https://mp.weixin.qq.com/s?__biz=MjM5NjQ4MjYwMQ==&mid=2664666070&idx=4&sn=1a34549b8ce1d691f161b4b75a6fb956", "create_at": "2022-09-11 01:27", "site_name": "\u5fae\u4fe1\u516c\u4f17\u53f7"}, {"id": 78119, "title": "[\u6c83\u514b\u5b66\u5b89\u5168] JAVA\u5b89\u5168|\u57fa\u7840\u7bc7\uff1a\u53cd\u5c04\u673a\u5236\u4e4b\u5e38\u89c1ReflectionAPI\u4f7f\u7528", "url": "https://mp.weixin.qq.com/s?__biz=MzkzMjIxNjExNg==&mid=2247484571&idx=1&sn=6264cec658e49abe22b12a7fbbe347ff", "create_at": "2022-09-11 01:27", "site_name": "\u5fae\u4fe1\u516c\u4f17\u53f7"}, {"id": 78118, "title": "[\u5a1c\u748bAI\u5b89\u5168\u4e4b\u5bb6] [\u7cfb\u7edf\u5b89\u5168] \u4e09\u5341\u516b.Metasploit\u540e\u6e17\u900f\u6280\u672f\u4fe1\u606f\u6536\u96c6\u3001\u6743\u9650\u63d0\u6743\u548c\u529f\u80fd\u6a21\u5757\u8be6\u89e3\u53ca\u9632\u62a4\u5efa\u8bae", "url": "https://mp.weixin.qq.com/s?__biz=Mzg5MTM5ODU2Mg==&mid=2247496994&idx=1&sn=df0d33c75ae06dbfcfe2c7082c7757b8", "create_at": "2022-09-11 01:27", "site_name": "\u5fae\u4fe1\u516c\u4f17\u53f7"}, {"id": 78117, "title": "[\u5168\u6808\u7f51\u7edc\u7a7a\u95f4\u5b89\u5168] \u4e2d\u79cb\u5feb\u4e50\uff01", "url": "https://mp.weixin.qq.com/s?__biz=Mzg3NTUzOTg3NA==&mid=2247504104&idx=1&sn=91e2b5c903ff6af697faf0b0e25eedbb", "create_at": "2022-09-11 01:27", "site_name": "\u5fae\u4fe1\u516c\u4f17\u53f7"}, {"id": 78116, "title": "[0x4d5a] Rust \u5b8f\u7cfb\u7edf\u5b9e\u73b0\u9ad8\u9636 Win32 API \u52a8\u6001\u5bfc\u5165", "url": "https://mp.weixin.qq.com/s?__biz=Mzg5MjU2NTc1Mg==&mid=2247483783&idx=1&sn=9145686b826e3d7cd4be263b323aa9cd", "create_at": "2022-09-11 01:27", "site_name": "\u5fae\u4fe1\u516c\u4f17\u53f7"}]