[{"id": 89029, "title": "\u8f66\u8054\u7f51\u5b89\u5168\u4e4bGPS\u6b3a\u9a97", "url": "https://www.freebuf.com/articles/network/386385.html", "create_at": "2023-12-24 10:23", "site_name": "freebuf"}, {"id": 89028, "title": "\u7ea2\u961f\u2014\u2014\u591a\u5c42\u5185\u7f51\u73af\u5883\u6e17\u900f\u6d4b\u8bd5\uff08\u4e09\uff09", "url": "https://www.freebuf.com/defense/382534.html", "create_at": "2023-12-24 10:23", "site_name": "freebuf"}, {"id": 89027, "title": "\u4e00\u5468\u7f51\u5b89\u4f18\u8d28PDF\u8d44\u6e90\u63a8\u8350\u4e28FreeBuf\u77e5\u8bc6\u5927\u9646", "url": "https://www.freebuf.com/news/387522.html", "create_at": "2023-12-24 09:53", "site_name": "freebuf"}, {"id": 89026, "title": "\u6837\u672c\u5206\u6790 | LockBit\uff1a\u6301\u7eed\u8fdb\u5316\u7684\u52d2\u7d22\u5a01\u80c1", "url": "https://www.freebuf.com/articles/es/386715.html", "create_at": "2023-12-24 08:43", "site_name": "freebuf"}]