[{"id": 85992, "title": "eval5 \u524d\u7aef\u6c99\u7bb1\u9003\u9038\u4e0eCSP Bypass", "url": "https://blog.xlab.app/p/766bba8a/", "create_at": "2023-05-26 11:09", "site_name": "sec-wiki"}, {"id": 85991, "title": "FreeBuf \u65e9\u62a5 | AI\u201c\u9020\u8c23\u201d\u81f4\u79d1\u5927\u8baf\u98de\u80a1\u4ef7\u95ea\u5d29\uff1bSAS\u822a\u7a7a\u516c\u53f8\u88ab\u518d\u6b21\u5165\u4fb5", "url": "https://www.freebuf.com/news/367578.html", "create_at": "2023-05-26 10:01", "site_name": "freebuf"}, {"id": 85990, "title": "2023\u5e74\u6076\u610f\u8f6f\u4ef6\u8d8b\u52bf\u9884\u6d4b", "url": "https://www.freebuf.com/articles/paper/366509.html", "create_at": "2023-05-26 10:01", "site_name": "freebuf"}, {"id": 85989, "title": "\u6df1\u5165\u4e86\u89e3\u9488\u5bf9\u4e2d\u4e9a\u653b\u51fb\u7684\u65b0\u6076\u610f\u8f6f\u4ef6 DownEx", "url": "https://www.freebuf.com/articles/network/366861.html", "create_at": "2023-05-26 08:44", "site_name": "freebuf"}]