[{"id": 85566, "title": "\u591a\u529f\u80fd\u540e\u95e8 Devopt \u5f3a\u52bf\u6765\u88ad", "url": "https://www.freebuf.com/articles/network/364722.html", "create_at": "2023-05-04 10:29", "site_name": "freebuf"}, {"id": 85565, "title": "FreeBuf \u65e9\u62a5 | \u97e9\u7f8e\u7b7e\u7f72\u7f51\u7edc\u5b89\u5168\u5408\u4f5c\u6846\u67b6\u534f\u8bae\uff1bAPT35\u4f7f\u7528\u65b0\u578b\u6076\u610f\u8f6f\u4ef6BellaCiao", "url": "https://www.freebuf.com/news/365232.html", "create_at": "2023-05-04 09:58", "site_name": "freebuf"}, {"id": 85564, "title": "\u6697\u7f51\u6df1\u5ea6\u8c03\u67e5\uff1aGoogle Play\u6076\u610f\u8f6f\u4ef6\u7684\u4f9b\u6c42\u751f\u610f", "url": "https://www.freebuf.com/articles/paper/365149.html", "create_at": "2023-05-04 08:43", "site_name": "freebuf"}]