[{"id": 97055, "title": "\u4e09\u661f\u8bbe\u5907\u66dd\u51fa\u9ad8\u5371\u96f6\u65e5\u6f0f\u6d1e\uff0c\u5df2\u5728\u91ce\u5916\u88ab\u5229\u7528", "url": "https://www.freebuf.com/news/413479.html", "create_at": "2024-10-23 11:17", "site_name": "freebuf"}, {"id": 97054, "title": "\u653b\u51fb\u8005\u6b63\u6ee5\u7528Gophish\u4f20\u64ad\u8fdc\u7a0b\u8bbf\u95ee\u6728\u9a6c\u7a0b\u5e8f", "url": "https://www.freebuf.com/news/413485.html", "create_at": "2024-10-23 11:17", "site_name": "freebuf"}, {"id": 97053, "title": "\u4ec0\u4e48\u662f\u8d1f\u8d23\u4efb\u7684 Web \u670d\u52a1\u5668\u626b\u63cf\uff1f", "url": "https://mp.weixin.qq.com/s/VG7NGj-SY84qWFoCP3LO6Q", "create_at": "2024-10-23 10:13", "site_name": "sec-wiki"}, {"id": 97052, "title": "FreeBuf\u65e9\u62a5 | Meta \u91cd\u542f\u9762\u90e8\u8bc6\u522b\u6280\u672f\uff1b\u6ca1\u6709\u4e00\u4e2a\u5927\u578b AI \u6a21\u578b\u7b26\u5408\u6b27\u76df\u76d1\u7ba1\u6807\u51c6", "url": "https://www.freebuf.com/news/413466.html", "create_at": "2024-10-23 10:13", "site_name": "freebuf"}, {"id": 97051, "title": "K8s\u66dd9.8\u5206\u6f0f\u6d1e\uff0c\u9ed1\u5ba2\u53ef\u83b7\u5f97Root\u8bbf\u95ee\u6743\u9650", "url": "https://www.freebuf.com/news/413438.html", "create_at": "2024-10-23 10:13", "site_name": "freebuf"}, {"id": 97050, "title": "\u9ad8\u901a64\u6b3e\u82af\u7247\u5b58\u57280Day\u6f0f\u6d1e", "url": "https://www.freebuf.com/news/413449.html", "create_at": "2024-10-23 10:13", "site_name": "freebuf"}, {"id": 97049, "title": "\u5de5\u4e1a\u884c\u4e1a | \u5b89\u5168\u9632\u62a4\u5efa\u8bbe\u4f53\u7cfb", "url": "https://www.freebuf.com/consult/412951.html", "create_at": "2024-10-23 10:13", "site_name": "freebuf"}, {"id": 97048, "title": "\u67d0\u53cbNCCloud\u9ed1\u540d\u5355\u7ed5\u8fc7\u5206\u6790", "url": "https://www.freebuf.com/articles/web/412655.html", "create_at": "2024-10-23 08:53", "site_name": "freebuf"}]