[{"id": 95013, "title": "FreeBuf \u5468\u62a5 | \u6709 92% \u7684\u4f01\u4e1a\u66fe\u906d\u9047\u793e\u5de5\u653b\u51fb\uff1b\u62dc\u767b\u4e0b\u4ee4\u7981\u7528\u5361\u5df4\u65af\u57fa\u6740\u6bd2\u8f6f\u4ef6", "url": "https://www.freebuf.com/news/404097.html", "create_at": "2024-06-22 09:53", "site_name": "freebuf"}, {"id": 95012, "title": "\u8c23\u8a00\u7c89\u788e\u673a | \u4eba\u4f53\u5185\u5b89\u88c5\u7a83\u542c\u5668\u7684\u4e94\u79cd\u53ef\u80fd", "url": "https://www.freebuf.com/articles/neopoints/403551.html", "create_at": "2024-06-22 08:43", "site_name": "freebuf"}]