[{"id": 98498, "title": "2025 \u5e74\u7684\u7f51\u7edc\u5b89\u5168\uff1a \u5168\u7403\u51b2\u7a81\u3001\u6210\u719f\u7684\u4eba\u5de5\u667a\u80fd\u548c\u7fa4\u4f17\u7684\u667a\u6167", "url": "https://www.anquanke.com//post/id/303398", "create_at": "2025-01-10 10:16", "site_name": "\u5b89\u5168\u5ba2"}, {"id": 98497, "title": "\u672a\u4fee\u8865\u7684\u5173\u952e\u7f3a\u9677\u5f71\u54cd Fancy Product Designer WordPress \u63d2\u4ef6", "url": "https://www.anquanke.com//post/id/303401", "create_at": "2025-01-10 10:16", "site_name": "\u5b89\u5168\u5ba2"}, {"id": 98496, "title": "SonicWall \u6566\u4fc3\u7ba1\u7406\u5458\u7acb\u5373\u4fee\u8865\u53ef\u88ab\u5229\u7528\u7684 SSLVPN \u6f0f\u6d1e", "url": "https://www.anquanke.com//post/id/303404", "create_at": "2025-01-10 10:16", "site_name": "\u5b89\u5168\u5ba2"}, {"id": 98495, "title": "\u9ed1\u5ba2\u5229\u7528 KerioControl \u9632\u706b\u5899\u6f0f\u6d1e\u7a83\u53d6\u7ba1\u7406\u5458 CSRF \u6807\u8bb0", "url": "https://www.anquanke.com//post/id/303408", "create_at": "2025-01-10 10:16", "site_name": "\u5b89\u5168\u5ba2"}, {"id": 98494, "title": "\u533b\u7597\u8ba1\u8d39\u516c\u53f8 Medusind \u62ab\u9732\u6f0f\u6d1e\u5f71\u54cd 36 \u4e07\u4eba", "url": "https://www.anquanke.com//post/id/303411", "create_at": "2025-01-10 10:16", "site_name": "\u5b89\u5168\u5ba2"}, {"id": 98493, "title": "\u8054\u5408\u56fd\u822a\u7a7a\u673a\u6784\u786e\u8ba4\u62db\u8058\u6570\u636e\u5e93\u5b58\u5728\u5b89\u5168\u6f0f\u6d1e", "url": "https://www.anquanke.com//post/id/303414", "create_at": "2025-01-10 10:16", "site_name": "\u5b89\u5168\u5ba2"}, {"id": 98492, "title": "FreeBuf\u65e9\u62a5 | \u6b27\u76df\u56e0\u8fdd\u53cd\u81ea\u8eab\u6570\u636e\u4fdd\u62a4\u6cd5\u88ab\u7f5a\uff1bIvanti VPN\u96f6\u65e5\u6f0f\u6d1e\u88ab\u79ef\u6781\u5229\u7528", "url": "https://www.freebuf.com/news/419403.html", "create_at": "2025-01-10 10:16", "site_name": "freebuf"}, {"id": 98491, "title": "\u7ecf\u9a8c\u5206\u4eab | \u6d45\u8c08Java\u5185\u5b58\u9a6c", "url": "https://www.freebuf.com/defense/419040.html", "create_at": "2025-01-10 10:16", "site_name": "freebuf"}, {"id": 98490, "title": "\u4e8c\u8fdb\u5236\u5b89\u5168\u5165\u95e8", "url": "https://www.freebuf.com/articles/system/419416.html", "create_at": "2025-01-10 08:55", "site_name": "freebuf"}]